dialoger/__init__.py
dialoger/input.py
dialoger/options.py
dialoger/images/alert.ico
dialoger/images/alert.png
dialoger/images/error.ico
dialoger/images/error.png
dialoger/images/info.ico
dialoger/images/info.png
dialoger/images/question.ico
dialoger/images/question.png
dialoger/images/success.ico
dialoger/images/success.png
dialoger-1.3.0.dist-info/LICENSE
dialoger-1.3.0.dist-info/METADATA
dialoger-1.3.0.dist-info/WHEEL
dialoger-1.3.0.dist-info/top_level.txt
dialoger-1.3.0.dist-info/RECORD
