Metadata-Version: 2.1
Name: dialoger
Version: 1.3.0
Summary: A package that provides a simple and user-friendly interface for creating interactive windows in Tkinter. Provides functions to create input windows, option list windows, alerts, information, errors and confirmation windows with options. Simplify user interaction with your program quickly and efficiently. One of the main functions is that it is possible to use patterns for certain answers, which allows requiring the user to have a date pattern, or input of numbers.
Home-page: https://github.com/guisaldanha/dialoger
Author: Guilherme Saldanha
Author-email: guisaldanha@gmail.com
License: MIT
Keywords: tkinter,dialog,dialoger,dialogbox,dialogboxer,dialoguer,dialoguerbox,box,user interface,interactive,input,choices,alert,information,error,confirmation,easy-to-use,efficiency,user-friendly,pattern,date,number,date pattern,number pattern,pattern input,pattern input date,pattern input number
Classifier: Intended Audience :: Developers
Classifier: License :: Freely Distributable
Classifier: Operating System :: Microsoft :: Windows
Classifier: Operating System :: Unix
Classifier: Programming Language :: Python :: 3.11
Classifier: Topic :: Communications
Classifier: Topic :: Utilities
License-File: LICENSE
